pyaprilaire/__init__.py
pyaprilaire/client.py
pyaprilaire/const.py
pyaprilaire/mock_server.py
pyaprilaire/packet.py
pyaprilaire/socket_client.py
pyaprilaire/test_connection.py
pyaprilaire-0.9.1.dist-info/licenses/LICENSE
pyaprilaire-0.9.1.dist-info/METADATA
pyaprilaire-0.9.1.dist-info/WHEEL
pyaprilaire-0.9.1.dist-info/top_level.txt
pyaprilaire-0.9.1.dist-info/RECORD
