Metadata-Version: 2.4
Name: pyaprilaire
Version: 0.9.1
Classifier: License :: OSI Approved :: MIT License
License-File: LICENSE
Requires-Dist: crc>=4
Provides-Extra: dev
Requires-Dist: black; extra == "dev"
Requires-Dist: bumpver; extra == "dev"
Requires-Dist: isort; extra == "dev"
Requires-Dist: pip-tools; extra == "dev"
Requires-Dist: pytest-asyncio; extra == "dev"
Requires-Dist: pytest-cov; extra == "dev"
Dynamic: license-file
